{"frames": {

"00_aNursesCalling":
{
	"frame": {"x":283,"y":302,"w":84,"h":66},
	"rotated": true,
	"trimmed": true,
	"spriteSourceSize": {"x":24,"y":29,"w":84,"h":66},
	"sourceSize": {"w":128,"h":128}
},
"01_agitation":
{
	"frame": {"x":283,"y":388,"w":80,"h":66},
	"rotated": true,
	"trimmed": true,
	"spriteSourceSize": {"x":25,"y":35,"w":80,"h":66},
	"sourceSize": {"w":128,"h":128}
},
"02_bamboozle":
{
	"frame": {"x":794,"y":350,"w":90,"h":85},
	"rotated": false,
	"trimmed": true,
	"spriteSourceSize": {"x":18,"y":27,"w":90,"h":85},
	"sourceSize": {"w":128,"h":128}
},
"03_barbecueAndChilli":
{
	"frame": {"x":542,"y":180,"w":81,"h":97},
	"rotated": false,
	"trimmed": true,
	"spriteSourceSize": {"x":21,"y":18,"w":81,"h":97},
	"sourceSize": {"w":128,"h":128}
},
"04_beastOfPrey":
{
	"frame": {"x":1050,"y":85,"w":85,"h":77},
	"rotated": false,
	"trimmed": true,
	"spriteSourceSize": {"x":29,"y":28,"w":85,"h":77},
	"sourceSize": {"w":128,"h":128}
},
"05_bitterMurmur":
{
	"frame": {"x":1135,"y":243,"w":83,"h":80},
	"rotated": false,
	"trimmed": true,
	"spriteSourceSize": {"x":17,"y":30,"w":83,"h":80},
	"sourceSize": {"w":128,"h":128}
},
"06_bloodWarden":
{
	"frame": {"x":351,"y":375,"w":93,"h":92},
	"rotated": true,
	"trimmed": true,
	"spriteSourceSize": {"x":16,"y":22,"w":93,"h":92},
	"sourceSize": {"w":128,"h":128}
},
"07_bloodhound":
{
	"frame": {"x":1225,"y":441,"w":65,"h":78},
	"rotated": true,
	"trimmed": true,
	"spriteSourceSize": {"x":30,"y":25,"w":65,"h":78},
	"sourceSize": {"w":128,"h":128}
},
"08_brutalStrength":
{
	"frame": {"x":886,"y":439,"w":88,"h":66},
	"rotated": false,
	"trimmed": true,
	"spriteSourceSize": {"x":18,"y":30,"w":88,"h":66},
	"sourceSize": {"w":128,"h":128}
},
"09_corruptIntervention":
{
	"frame": {"x":878,"y":165,"w":85,"h":90},
	"rotated": false,
	"trimmed": true,
	"spriteSourceSize": {"x":21,"y":20,"w":85,"h":90},
	"sourceSize": {"w":128,"h":128}
},
"10_coulrophobia":
{
	"frame": {"x":218,"y":107,"w":91,"h":91},
	"rotated": false,
	"trimmed": true,
	"spriteSourceSize": {"x":20,"y":20,"w":91,"h":91},
	"sourceSize": {"w":128,"h":128}
},
"11_darkDevotion":
{
	"frame": {"x":539,"y":377,"w":92,"h":92},
	"rotated": false,
	"trimmed": true,
	"spriteSourceSize": {"x":18,"y":19,"w":92,"h":92},
	"sourceSize": {"w":128,"h":128}
},
"12_deerstalker":
{
	"frame": {"x":1321,"y":97,"w":65,"h":92},
	"rotated": true,
	"trimmed": true,
	"spriteSourceSize": {"x":32,"y":21,"w":65,"h":92},
	"sourceSize": {"w":128,"h":128}
},
"13_discordance":
{
	"frame": {"x":1319,"y":164,"w":61,"h":90},
	"rotated": true,
	"trimmed": true,
	"spriteSourceSize": {"x":33,"y":15,"w":61,"h":90},
	"sourceSize": {"w":128,"h":128}
},
"14_distressing":
{
	"frame": {"x":962,"y":88,"w":86,"h":73},
	"rotated": false,
	"trimmed": true,
	"spriteSourceSize": {"x":23,"y":27,"w":86,"h":73},
	"sourceSize": {"w":128,"h":128}
},
"15_dyingLight":
{
	"frame": {"x":1225,"y":358,"w":76,"h":81},
	"rotated": false,
	"trimmed": true,
	"spriteSourceSize": {"x":27,"y":23,"w":76,"h":81},
	"sourceSize": {"w":128,"h":128}
},
"16_enduring":
{
	"frame": {"x":976,"y":435,"w":68,"h":88},
	"rotated": true,
	"trimmed": true,
	"spriteSourceSize": {"x":29,"y":20,"w":68,"h":88},
	"sourceSize": {"w":128,"h":128}
},
"17_fireUp":
{
	"frame": {"x":341,"y":100,"w":72,"h":105},
	"rotated": true,
	"trimmed": true,
	"spriteSourceSize": {"x":26,"y":9,"w":72,"h":105},
	"sourceSize": {"w":128,"h":128}
},
"18_franklinsDemise":
{
	"frame": {"x":1051,"y":250,"w":83,"h":82},
	"rotated": true,
	"trimmed": true,
	"spriteSourceSize": {"x":20,"y":19,"w":83,"h":82},
	"sourceSize": {"w":128,"h":128}
},
"19_hangmansTrick":
{
	"frame": {"x":182,"y":302,"w":99,"h":70},
	"rotated": false,
	"trimmed": true,
	"spriteSourceSize": {"x":11,"y":30,"w":99,"h":70},
	"sourceSize": {"w":128,"h":128}
},
"20_hexDevourHope":
{
	"frame": {"x":1305,"y":437,"w":63,"h":73},
	"rotated": true,
	"trimmed": true,
	"spriteSourceSize": {"x":33,"y":30,"w":63,"h":73},
	"sourceSize": {"w":128,"h":128}
},
"21_hexHauntedGround":
{
	"frame": {"x":889,"y":1,"w":85,"h":111},
	"rotated": true,
	"trimmed": true,
	"spriteSourceSize": {"x":22,"y":7,"w":85,"h":111},
	"sourceSize": {"w":128,"h":128}
},
"22_hexHuntressLullaby":
{
	"frame": {"x":193,"y":374,"w":88,"h":88},
	"rotated": false,
	"trimmed": true,
	"spriteSourceSize": {"x":18,"y":15,"w":88,"h":88},
	"sourceSize": {"w":128,"h":128}
},
"23_hexNoOneEscapesDeath":
{
	"frame": {"x":886,"y":93,"w":74,"h":70},
	"rotated": false,
	"trimmed": true,
	"spriteSourceSize": {"x":28,"y":25,"w":74,"h":70},
	"sourceSize": {"w":128,"h":128}
},
"24_hexRuin":
{
	"frame": {"x":1304,"y":294,"w":81,"h":76},
	"rotated": false,
	"trimmed": true,
	"spriteSourceSize": {"x":26,"y":26,"w":81,"h":76},
	"sourceSize": {"w":128,"h":128}
},
"25_hexTheThirdSeal":
{
	"frame": {"x":1313,"y":227,"w":65,"h":83},
	"rotated": true,
	"trimmed": true,
	"spriteSourceSize": {"x":33,"y":22,"w":65,"h":83},
	"sourceSize": {"w":128,"h":128}
},
"26_hexThrillOfTheHunt":
{
	"frame": {"x":1137,"y":83,"w":78,"h":86},
	"rotated": true,
	"trimmed": true,
	"spriteSourceSize": {"x":24,"y":25,"w":78,"h":86},
	"sourceSize": {"w":128,"h":128}
},
"27_infectiousFright":
{
	"frame": {"x":116,"y":107,"w":100,"h":91},
	"rotated": false,
	"trimmed": true,
	"spriteSourceSize": {"x":15,"y":23,"w":100,"h":91},
	"sourceSize": {"w":128,"h":128}
},
"28_insidious":
{
	"frame": {"x":975,"y":345,"w":80,"h":88},
	"rotated": false,
	"trimmed": true,
	"spriteSourceSize": {"x":25,"y":14,"w":80,"h":88},
	"sourceSize": {"w":128,"h":128}
},
"29_ironGrasp":
{
	"frame": {"x":790,"y":437,"w":94,"h":64},
	"rotated": false,
	"trimmed": true,
	"spriteSourceSize": {"x":15,"y":29,"w":94,"h":64},
	"sourceSize": {"w":128,"h":128}
},
"30_ironMaiden":
{
	"frame": {"x":1303,"y":372,"w":63,"h":80},
	"rotated": true,
	"trimmed": true,
	"spriteSourceSize": {"x":32,"y":19,"w":63,"h":80},
	"sourceSize": {"w":128,"h":128}
},
"31_knockOut":
{
	"frame": {"x":724,"y":374,"w":64,"h":95},
	"rotated": false,
	"trimmed": true,
	"spriteSourceSize": {"x":31,"y":21,"w":64,"h":95},
	"sourceSize": {"w":128,"h":128}
},
"32_lightborn":
{
	"frame": {"x":1225,"y":160,"w":92,"h":64},
	"rotated": false,
	"trimmed": true,
	"spriteSourceSize": {"x":17,"y":33,"w":92,"h":64},
	"sourceSize": {"w":128,"h":128}
},
"33_madGrit":
{
	"frame": {"x":1,"y":1,"w":113,"h":110},
	"rotated": false,
	"trimmed": true,
	"spriteSourceSize": {"x":4,"y":12,"w":113,"h":110},
	"sourceSize": {"w":128,"h":128}
},
"34_makeYourChoice":
{
	"frame": {"x":104,"y":433,"w":73,"h":87},
	"rotated": true,
	"trimmed": true,
	"spriteSourceSize": {"x":28,"y":25,"w":73,"h":87},
	"sourceSize": {"w":128,"h":128}
},
"35_monitorAndAbuse":
{
	"frame": {"x":1118,"y":1,"w":110,"h":80},
	"rotated": false,
	"trimmed": true,
	"spriteSourceSize": {"x":11,"y":21,"w":110,"h":80},
	"sourceSize": {"w":128,"h":128}
},
"36_monstrousShrine":
{
	"frame": {"x":631,"y":278,"w":81,"h":97},
	"rotated": false,
	"trimmed": true,
	"spriteSourceSize": {"x":23,"y":5,"w":81,"h":97},
	"sourceSize": {"w":128,"h":128}
},
"37_overcharge":
{
	"frame": {"x":1137,"y":163,"w":78,"h":86},
	"rotated": true,
	"trimmed": true,
	"spriteSourceSize": {"x":27,"y":24,"w":78,"h":86},
	"sourceSize": {"w":128,"h":128}
},
"38_overwhelmingPresence":
{
	"frame": {"x":787,"y":165,"w":89,"h":90},
	"rotated": false,
	"trimmed": true,
	"spriteSourceSize": {"x":19,"y":19,"w":89,"h":90},
	"sourceSize": {"w":128,"h":128}
},
"39_playWithYourFood":
{
	"frame": {"x":1136,"y":325,"w":79,"h":83},
	"rotated": false,
	"trimmed": true,
	"spriteSourceSize": {"x":24,"y":24,"w":79,"h":83},
	"sourceSize": {"w":128,"h":128}
},
"40_popGoesTheWeasel":
{
	"frame": {"x":182,"y":200,"w":79,"h":100},
	"rotated": false,
	"trimmed": true,
	"spriteSourceSize": {"x":25,"y":14,"w":79,"h":100},
	"sourceSize": {"w":128,"h":128}
},
"41_predator":
{
	"frame": {"x":346,"y":174,"w":96,"h":99},
	"rotated": false,
	"trimmed": true,
	"spriteSourceSize": {"x":13,"y":14,"w":96,"h":99},
	"sourceSize": {"w":128,"h":128}
},
"42_rancor":
{
	"frame": {"x":443,"y":276,"w":94,"h":95},
	"rotated": false,
	"trimmed": true,
	"spriteSourceSize": {"x":17,"y":17,"w":94,"h":95},
	"sourceSize": {"w":128,"h":128}
},
"43_rememberMe":
{
	"frame": {"x":1048,"y":164,"w":84,"h":84},
	"rotated": false,
	"trimmed": true,
	"spriteSourceSize": {"x":22,"y":21,"w":84,"h":84},
	"sourceSize": {"w":128,"h":128}
},
"44_saveTheBestForLast":
{
	"frame": {"x":565,"y":99,"w":79,"h":92},
	"rotated": true,
	"trimmed": true,
	"spriteSourceSize": {"x":25,"y":24,"w":79,"h":92},
	"sourceSize": {"w":128,"h":128}
},
"45_shadowborn":
{
	"frame": {"x":1,"y":447,"w":93,"h":59},
	"rotated": false,
	"trimmed": true,
	"spriteSourceSize": {"x":20,"y":34,"w":93,"h":59},
	"sourceSize": {"w":128,"h":128}
},
"46_sloppyButcher":
{
	"frame": {"x":1380,"y":438,"w":70,"h":66},
	"rotated": false,
	"trimmed": true,
	"spriteSourceSize": {"x":29,"y":32,"w":70,"h":66},
	"sourceSize": {"w":128,"h":128}
},
"47_spiesFromTheShadows":
{
	"frame": {"x":1385,"y":372,"w":79,"h":64},
	"rotated": false,
	"trimmed": true,
	"spriteSourceSize": {"x":25,"y":39,"w":79,"h":64},
	"sourceSize": {"w":128,"h":128}
},
"48_spiritFury":
{
	"frame": {"x":659,"y":100,"w":98,"h":78},
	"rotated": false,
	"trimmed": true,
	"spriteSourceSize": {"x":14,"y":22,"w":98,"h":78},
	"sourceSize": {"w":128,"h":128}
},
"49_stridor":
{
	"frame": {"x":263,"y":200,"w":100,"h":81},
	"rotated": true,
	"trimmed": true,
	"spriteSourceSize": {"x":18,"y":15,"w":100,"h":81},
	"sourceSize": {"w":128,"h":128}
},
"50_surveillance":
{
	"frame": {"x":1225,"y":93,"w":65,"h":94},
	"rotated": true,
	"trimmed": true,
	"spriteSourceSize": {"x":33,"y":22,"w":65,"h":94},
	"sourceSize": {"w":128,"h":128}
},
"51_territorialImperative":
{
	"frame": {"x":972,"y":253,"w":77,"h":90},
	"rotated": false,
	"trimmed": true,
	"spriteSourceSize": {"x":23,"y":20,"w":77,"h":90},
	"sourceSize": {"w":128,"h":128}
},
"52_thanatophobia":
{
	"frame": {"x":1147,"y":410,"w":76,"h":84},
	"rotated": false,
	"trimmed": true,
	"spriteSourceSize": {"x":26,"y":21,"w":76,"h":84},
	"sourceSize": {"w":128,"h":128}
},
"53_tinkerer":
{
	"frame": {"x":1387,"y":294,"w":76,"h":80},
	"rotated": true,
	"trimmed": true,
	"spriteSourceSize": {"x":27,"y":15,"w":76,"h":80},
	"sourceSize": {"w":128,"h":128}
},
"54_unnervingPresence":
{
	"frame": {"x":965,"y":163,"w":81,"h":88},
	"rotated": false,
	"trimmed": true,
	"spriteSourceSize": {"x":23,"y":12,"w":81,"h":88},
	"sourceSize": {"w":128,"h":128}
},
"55_unrelenting":
{
	"frame": {"x":1066,"y":424,"w":79,"h":82},
	"rotated": false,
	"trimmed": true,
	"spriteSourceSize": {"x":28,"y":22,"w":79,"h":82},
	"sourceSize": {"w":128,"h":128}
},
"56_whispers":
{
	"frame": {"x":633,"y":377,"w":89,"h":92},
	"rotated": false,
	"trimmed": true,
	"spriteSourceSize": {"x":23,"y":24,"w":89,"h":92},
	"sourceSize": {"w":128,"h":128}
},
"57_imAllEars":
{
	"frame": {"x":445,"y":373,"w":92,"h":95},
	"rotated": false,
	"trimmed": true,
	"spriteSourceSize": {"x":10,"y":20,"w":92,"h":95},
	"sourceSize": {"w":128,"h":128}
},
"58_thrillingTremors":
{
	"frame": {"x":714,"y":278,"w":78,"h":94},
	"rotated": false,
	"trimmed": true,
	"spriteSourceSize": {"x":24,"y":20,"w":78,"h":94},
	"sourceSize": {"w":128,"h":128}
},
"59_furtiveChase":
{
	"frame": {"x":351,"y":275,"w":90,"h":98},
	"rotated": false,
	"trimmed": true,
	"spriteSourceSize": {"x":19,"y":9,"w":90,"h":98},
	"sourceSize": {"w":128,"h":128}
},
"60_cruelLimits":
{
	"frame": {"x":1002,"y":1,"w":82,"h":114},
	"rotated": true,
	"trimmed": true,
	"spriteSourceSize": {"x":24,"y":7,"w":82,"h":114},
	"sourceSize": {"w":128,"h":128}
},
"61_mindbreaker":
{
	"frame": {"x":1,"y":113,"w":112,"h":111},
	"rotated": false,
	"trimmed": true,
	"spriteSourceSize": {"x":7,"y":11,"w":112,"h":111},
	"sourceSize": {"w":128,"h":128}
},
"62_surge":
{
	"frame": {"x":456,"y":1,"w":107,"h":101},
	"rotated": false,
	"trimmed": true,
	"spriteSourceSize": {"x":12,"y":14,"w":107,"h":101},
	"sourceSize": {"w":128,"h":128}
},
"63_bloodEcho":
{
	"frame": {"x":1057,"y":335,"w":77,"h":87},
	"rotated": false,
	"trimmed": true,
	"spriteSourceSize": {"x":25,"y":22,"w":77,"h":87},
	"sourceSize": {"w":128,"h":128}
},
"64_nemesis":
{
	"frame": {"x":539,"y":279,"w":96,"h":90},
	"rotated": true,
	"trimmed": true,
	"spriteSourceSize": {"x":16,"y":19,"w":96,"h":90},
	"sourceSize": {"w":128,"h":128}
},
"65_zanshinTactics":
{
	"frame": {"x":673,"y":1,"w":97,"h":103},
	"rotated": true,
	"trimmed": true,
	"spriteSourceSize": {"x":13,"y":6,"w":97,"h":103},
	"sourceSize": {"w":128,"h":128}
},
"66_gearhead":
{
	"frame": {"x":1220,"y":293,"w":63,"h":82},
	"rotated": true,
	"trimmed": true,
	"spriteSourceSize": {"x":32,"y":26,"w":63,"h":82},
	"sourceSize": {"w":128,"h":128}
},
"67_deadMansSwitch":
{
	"frame": {"x":1,"y":226,"w":105,"h":108},
	"rotated": false,
	"trimmed": true,
	"spriteSourceSize": {"x":13,"y":12,"w":105,"h":108},
	"sourceSize": {"w":128,"h":128}
},
"68_hexRetribution":
{
	"frame": {"x":1,"y":336,"w":101,"h":109},
	"rotated": false,
	"trimmed": true,
	"spriteSourceSize": {"x":16,"y":13,"w":101,"h":109},
	"sourceSize": {"w":128,"h":128}
},
"69_forcedPenance":
{
	"frame": {"x":778,"y":93,"w":70,"h":106},
	"rotated": true,
	"trimmed": true,
	"spriteSourceSize": {"x":26,"y":8,"w":70,"h":106},
	"sourceSize": {"w":128,"h":128}
},
"70_trailOfTorment":
{
	"frame": {"x":883,"y":257,"w":87,"h":89},
	"rotated": false,
	"trimmed": true,
	"spriteSourceSize": {"x":20,"y":17,"w":87,"h":89},
	"sourceSize": {"w":128,"h":128}
},
"71_deathbound":
{
	"frame": {"x":1225,"y":226,"w":65,"h":86},
	"rotated": true,
	"trimmed": true,
	"spriteSourceSize": {"x":33,"y":23,"w":65,"h":86},
	"sourceSize": {"w":128,"h":128}
},
"72_hexBloodFavour":
{
	"frame": {"x":778,"y":1,"w":109,"h":90},
	"rotated": false,
	"trimmed": true,
	"spriteSourceSize": {"x":9,"y":24,"w":109,"h":90},
	"sourceSize": {"w":128,"h":128}
},
"73_hexUndying":
{
	"frame": {"x":565,"y":1,"w":96,"h":106},
	"rotated": true,
	"trimmed": true,
	"spriteSourceSize": {"x":9,"y":9,"w":96,"h":106},
	"sourceSize": {"w":128,"h":128}
},
"74_dragonsGrip":
{
	"frame": {"x":444,"y":180,"w":96,"h":94},
	"rotated": false,
	"trimmed": true,
	"spriteSourceSize": {"x":16,"y":19,"w":96,"h":94},
	"sourceSize": {"w":128,"h":128}
},
"75_hoarder":
{
	"frame": {"x":1335,"y":1,"w":101,"h":94},
	"rotated": false,
	"trimmed": true,
	"spriteSourceSize": {"x":21,"y":24,"w":101,"h":94},
	"sourceSize": {"w":128,"h":128}
},
"76_oppression":
{
	"frame": {"x":720,"y":180,"w":96,"h":65},
	"rotated": true,
	"trimmed": true,
	"spriteSourceSize": {"x":19,"y":30,"w":96,"h":65},
	"sourceSize": {"w":128,"h":128}
},
"77_coupDeGrace":
{
	"frame": {"x":794,"y":257,"w":91,"h":87},
	"rotated": true,
	"trimmed": true,
	"spriteSourceSize": {"x":15,"y":28,"w":91,"h":87},
	"sourceSize": {"w":128,"h":128}
},
"78_starstruck":
{
	"frame": {"x":1230,"y":1,"w":90,"h":103},
	"rotated": true,
	"trimmed": true,
	"spriteSourceSize": {"x":23,"y":18,"w":90,"h":103},
	"sourceSize": {"w":128,"h":128}
},
"79_hexCrowdControl":
{
	"frame": {"x":230,"y":1,"w":109,"h":103},
	"rotated": false,
	"trimmed": true,
	"spriteSourceSize": {"x":9,"y":18,"w":109,"h":103},
	"sourceSize": {"w":128,"h":128}
},
"80_noWayOut":
{
	"frame": {"x":886,"y":348,"w":87,"h":89},
	"rotated": false,
	"trimmed": true,
	"spriteSourceSize": {"x":19,"y":19,"w":87,"h":89},
	"sourceSize": {"w":128,"h":128}
},
"81_eruption":
{
	"frame": {"x":108,"y":226,"w":72,"h":107},
	"rotated": false,
	"trimmed": true,
	"spriteSourceSize": {"x":27,"y":9,"w":72,"h":107},
	"sourceSize": {"w":128,"h":128}
},
"82_hysteria":
{
	"frame": {"x":341,"y":1,"w":113,"h":97},
	"rotated": false,
	"trimmed": true,
	"spriteSourceSize": {"x":7,"y":21,"w":113,"h":97},
	"sourceSize": {"w":128,"h":128}
},
"83_lethalPursuer":
{
	"frame": {"x":625,"y":180,"w":93,"h":96},
	"rotated": false,
	"trimmed": true,
	"spriteSourceSize": {"x":16,"y":18,"w":93,"h":96},
	"sourceSize": {"w":128,"h":128}
},
"84_Deadlock":
{
	"frame": {"x":104,"y":336,"w":76,"h":95},
	"rotated": false,
	"trimmed": true,
	"spriteSourceSize": {"x":27,"y":16,"w":76,"h":95},
	"sourceSize": {"w":128,"h":128}
},
"85_HexPlaything":
{
	"frame": {"x":448,"y":104,"w":74,"h":104},
	"rotated": true,
	"trimmed": true,
	"spriteSourceSize": {"x":30,"y":20,"w":74,"h":104},
	"sourceSize": {"w":128,"h":128}
},
"86_ScourgeHookGiftOfPain":
{
	"frame": {"x":116,"y":1,"w":112,"h":104},
	"rotated": false,
	"trimmed": true,
	"spriteSourceSize": {"x":7,"y":11,"w":112,"h":104},
	"sourceSize": {"w":128,"h":128}
}},
"meta": {
	"app": "https://www.codeandweb.com/texturepacker",
	"version": "1.0",
	"image": "kill-md.png",
	"format": "RGBA8888",
	"size": {"w":1468,"h":507},
	"scale": "0.5",
	"smartupdate": "$TexturePacker:SmartUpdate:cee68a4826127303f23949d412dd2ce4:4e7731a1d815c4f99d0a1aed1615dd7c:c7b4df0161df714ccaa6c5dcf6c4cd5b$"
}
}
